{
  "title": "Sonnets—Realities II",
  "first_line": "my strength becoming wistful in a glib",
  "text": "my strength becoming wistful in a glib\n\ngirl i consider her a leaf\n                           thinks\nof the sky, my mind takes to nib\n-bling,of her posture.  (As an eye winks).\n\nand almost i refrain from jumbling her\nflesh whose casual mouth’s coy rooting\ndies also.  (my loveFist in her knuckling\n\nthighs,\n       with a sharp indecent stir\nunclenches\n\n            into fingers....she too is tired.\nNot of me.   The eyes which biggish loll\n\nthe hands’ will tumbling into shall\n\n—and Love ’s a coach with gilt hopeless wheels mired\nwhere sits rigidly her body’s doll\ngay exactly perishing sexual,",
  "slug": "sonnets-realities-ii",
  "description": "my strength becoming wistful in a glib",
  "seo_title": "my strength becoming wistful in a glib",
  "seo_description": "A poem by E. E. Cummings in “&”",
  "html_url": "https://cummings.ee/book/and/poem/sonnets-realities-ii/",
  "json_url": "https://cummings.ee/book/and/poem/sonnets-realities-ii.json",
  "txt_url": "https://cummings.ee/book/and/poem/sonnets-realities-ii.txt"
}
